[{"date": "15-09-2020", "nav": "59.04590"}, {"date": "15-07-2020", "nav": "59.41190"}, {"date": "15-06-2020", "nav": "58.37620"}, {"date": "15-05-2020", "nav": "57.64520"}, {"date": "15-04-2020", "nav": "55.90430"}, {"date": "15-01-2020", "nav": "54.33170"}, {"date": "15-11-2019", "nav": "54.04390"}, {"date": "15-10-2019", "nav": "53.79410"}, {"date": "15-07-2019", "nav": "53.58410"}, {"date": "15-05-2019", "nav": "50.98690"}, {"date": "15-04-2019", "nav": "50.69000"}, {"date": "15-03-2019", "nav": "50.20610"}, {"date": "15-02-2019", "nav": "49.63030"}, {"date": "15-01-2019", "nav": "49.49560"}, {"date": "15-11-2018", "nav": "48.44140"}, {"date": "15-10-2018", "nav": "48.04980"}, {"date": "15-06-2018", "nav": "47.22120"}, {"date": "15-05-2018", "nav": "47.05440"}, {"date": "15-03-2018", "nav": "46.87370"}, {"date": "15-02-2018", "nav": "46.77980"}, {"date": "15-01-2018", "nav": "46.96750"}, {"date": "15-12-2017", "nav": "47.32560"}, {"date": "15-11-2017", "nav": "47.50240"}, {"date": "15-09-2017", "nav": "47.95320"}, {"date": "15-06-2017", "nav": "47.93940"}, {"date": "15-05-2017", "nav": "46.77480"}, {"date": "15-03-2017", "nav": "45.69080"}, {"date": "15-02-2017", "nav": "45.72530"}, {"date": "15-12-2016", "nav": "46.66910"}, {"date": "15-11-2016", "nav": "46.82210"}, {"date": "15-09-2016", "nav": "45.34340"}, {"date": "15-07-2016", "nav": "43.85030"}, {"date": "15-06-2016", "nav": "42.77080"}, {"date": "15-03-2016", "nav": "41.24080"}, {"date": "15-02-2016", "nav": "40.47180"}, {"date": "15-01-2016", "nav": "40.59050"}, {"date": "15-12-2015", "nav": "40.74340"}, {"date": "15-10-2015", "nav": "41.28090"}, {"date": "15-09-2015", "nav": "40.39460"}, {"date": "15-07-2015", "nav": "39.63990"}, {"date": "15-06-2015", "nav": "39.16690"}, {"date": "15-05-2015", "nav": "39.48540"}, {"date": "15-04-2015", "nav": "39.88230"}, {"date": "15-01-2015", "nav": "39.54820"}, {"date": "15-12-2014", "nav": "39.10070"}, {"date": "15-09-2014", "nav": "36.36380"}, {"date": "15-07-2014", "nav": "35.94380"}, {"date": "15-05-2014", "nav": "35.06730"}, {"date": "15-04-2014", "nav": "34.42320"}, {"date": "15-01-2014", "nav": "34.30590"}, {"date": "15-10-2013", "nav": "33.70590"}, {"date": "15-07-2013", "nav": "35.16350"}, {"date": "15-05-2013", "nav": "35.52930"}, {"date": "15-04-2013", "nav": "34.31430"}, {"date": "15-03-2013", "nav": "33.92920"}, {"date": "15-02-2013", "nav": "33.82180"}, {"date": "15-01-2013", "nav": "33.78130"}, {"date": "15-11-2012", "nav": "32.67640"}, {"date": "15-10-2012", "nav": "32.52800"}, {"date": "15-06-2012", "nav": "31.50840"}, {"date": "15-05-2012", "nav": "30.88230"}, {"date": "15-03-2012", "nav": "30.28800"}, {"date": "15-02-2012", "nav": "30.27750"}, {"date": "15-12-2011", "nav": "29.17470"}, {"date": "15-11-2011", "nav": "28.38940"}, {"date": "15-09-2011", "nav": "28.54470"}, {"date": "15-07-2011", "nav": "28.20160"}, {"date": "15-06-2011", "nav": "27.78110"}, {"date": "15-04-2011", "nav": "27.56270"}, {"date": "15-03-2011", "nav": "27.41230"}, {"date": "15-02-2011", "nav": "27.23420"}, {"date": "15-12-2010", "nav": "27.06340"}, {"date": "15-11-2010", "nav": "27.04280"}, {"date": "15-10-2010", "nav": "26.93820"}, {"date": "15-09-2010", "nav": "26.84360"}, {"date": "15-07-2010", "nav": "26.99110"}, {"date": "15-06-2010", "nav": "27.02910"}, {"date": "15-04-2010", "nav": "26.29590"}, {"date": "15-03-2010", "nav": "26.07150"}, {"date": "15-02-2010", "nav": "25.98100"}, {"date": "15-01-2010", "nav": "26.01720"}, {"date": "15-12-2009", "nav": "25.91630"}, {"date": "15-10-2009", "nav": "25.41720"}, {"date": "15-09-2009", "nav": "25.48260"}, {"date": "15-07-2009", "nav": "25.57850"}, {"date": "15-06-2009", "nav": "25.41280"}, {"date": "15-05-2009", "nav": "25.48160"}, {"date": "15-04-2009", "nav": "25.16870"}, {"date": "15-01-2009", "nav": "25.53820"}, {"date": "15-12-2008", "nav": "24.71540"}, {"date": "15-10-2008", "nav": "21.90750"}, {"date": "15-09-2008", "nav": "21.89970"}, {"date": "15-07-2008", "nav": "21.52520"}, {"date": "15-05-2008", "nav": "21.62030"}, {"date": "15-04-2008", "nav": "21.44590"}, {"date": "15-02-2008", "nav": "21.89960"}, {"date": "15-01-2008", "nav": "21.73180"}, {"date": "15-11-2007", "nav": "20.96840"}, {"date": "15-10-2007", "nav": "20.75460"}, {"date": "15-06-2007", "nav": "19.81840"}, {"date": "15-05-2007", "nav": "19.68960"}, {"date": "15-03-2007", "nav": "19.51610"}, {"date": "15-02-2007", "nav": "19.45960"}, {"date": "15-01-2007", "nav": "19.44640"}, {"date": "15-12-2006", "nav": "19.41090"}, {"date": "15-11-2006", "nav": "19.26900"}, {"date": "15-09-2006", "nav": "18.96130"}, {"date": "15-06-2006", "nav": "18.55570"}, {"date": "15-05-2006", "nav": "18.47690"}]