[{"date": "15-09-2020", "nav": "24.37910"}, {"date": "15-07-2020", "nav": "24.40560"}, {"date": "15-06-2020", "nav": "23.85480"}, {"date": "15-05-2020", "nav": "23.51150"}, {"date": "15-04-2020", "nav": "23.09690"}, {"date": "15-01-2020", "nav": "22.88080"}, {"date": "15-11-2019", "nav": "22.70510"}, {"date": "15-10-2019", "nav": "22.31730"}, {"date": "15-07-2019", "nav": "21.93600"}, {"date": "15-05-2019", "nav": "22.97820"}, {"date": "15-04-2019", "nav": "23.13320"}, {"date": "15-03-2019", "nav": "23.08310"}, {"date": "15-02-2019", "nav": "22.86370"}, {"date": "15-01-2019", "nav": "22.73880"}, {"date": "15-11-2018", "nav": "22.19180"}, {"date": "15-10-2018", "nav": "21.99400"}, {"date": "15-06-2018", "nav": "21.67870"}, {"date": "15-05-2018", "nav": "21.65470"}, {"date": "15-03-2018", "nav": "21.70850"}, {"date": "15-02-2018", "nav": "21.62730"}, {"date": "15-01-2018", "nav": "21.54020"}, {"date": "15-12-2017", "nav": "21.48480"}, {"date": "15-11-2017", "nav": "21.42090"}, {"date": "15-09-2017", "nav": "21.27000"}, {"date": "15-06-2017", "nav": "20.86260"}, {"date": "15-05-2017", "nav": "20.63170"}, {"date": "15-03-2017", "nav": "20.31590"}, {"date": "15-02-2017", "nav": "20.30610"}, {"date": "15-12-2016", "nav": "20.12810"}, {"date": "15-11-2016", "nav": "19.99900"}, {"date": "15-09-2016", "nav": "19.58830"}, {"date": "15-07-2016", "nav": "19.12890"}, {"date": "15-06-2016", "nav": "18.81360"}, {"date": "15-03-2016", "nav": "18.39780"}, {"date": "15-02-2016", "nav": "18.21260"}, {"date": "15-01-2016", "nav": "18.17670"}, {"date": "15-12-2015", "nav": "18.14120"}, {"date": "15-10-2015", "nav": "18.14570"}, {"date": "15-09-2015", "nav": "17.86840"}, {"date": "15-07-2015", "nav": "17.61650"}, {"date": "15-06-2015", "nav": "17.49090"}, {"date": "15-05-2015", "nav": "17.40570"}, {"date": "15-04-2015", "nav": "17.37730"}, {"date": "15-01-2015", "nav": "17.06660"}, {"date": "15-12-2014", "nav": "16.94800"}, {"date": "15-09-2014", "nav": "16.25300"}, {"date": "15-07-2014", "nav": "16.02800"}, {"date": "15-05-2014", "nav": "15.86160"}, {"date": "15-04-2014", "nav": "15.68160"}, {"date": "15-01-2014", "nav": "15.42160"}, {"date": "15-10-2013", "nav": "15.15130"}, {"date": "15-07-2013", "nav": "14.97450"}, {"date": "15-05-2013", "nav": "15.00950"}, {"date": "15-04-2013", "nav": "14.76890"}, {"date": "15-03-2013", "nav": "14.63130"}, {"date": "15-02-2013", "nav": "14.52690"}, {"date": "15-01-2013", "nav": "14.48560"}, {"date": "15-11-2012", "nav": "14.21900"}, {"date": "15-10-2012", "nav": "14.16170"}, {"date": "15-06-2012", "nav": "13.68770"}, {"date": "15-05-2012", "nav": "13.56760"}, {"date": "15-03-2012", "nav": "13.34790"}, {"date": "15-02-2012", "nav": "13.32530"}, {"date": "15-12-2011", "nav": "13.14570"}, {"date": "15-11-2011", "nav": "13.04440"}, {"date": "15-09-2011", "nav": "12.89230"}, {"date": "15-07-2011", "nav": "12.68000"}, {"date": "15-06-2011", "nav": "12.56270"}, {"date": "15-04-2011", "nav": "12.44580"}, {"date": "15-03-2011", "nav": "12.31200"}, {"date": "15-02-2011", "nav": "12.23020"}, {"date": "15-12-2010", "nav": "12.11110"}, {"date": "15-11-2010", "nav": "12.10270"}]