[{"date": "15-09-2020", "nav": "25.67280"}, {"date": "15-07-2020", "nav": "23.99140"}, {"date": "15-06-2020", "nav": "22.74340"}, {"date": "15-05-2020", "nav": "22.10780"}, {"date": "15-04-2020", "nav": "21.63850"}, {"date": "15-01-2020", "nav": "25.07070"}, {"date": "15-11-2019", "nav": "23.98770"}, {"date": "15-10-2019", "nav": "23.30190"}, {"date": "15-07-2019", "nav": "23.46350"}, {"date": "15-05-2019", "nav": "22.78970"}, {"date": "15-04-2019", "nav": "23.61480"}, {"date": "15-03-2019", "nav": "23.30060"}, {"date": "15-02-2019", "nav": "22.13050"}, {"date": "15-01-2019", "nav": "22.74340"}, {"date": "15-11-2018", "nav": "22.39720"}, {"date": "15-10-2018", "nav": "22.02910"}, {"date": "15-06-2018", "nav": "22.85650"}, {"date": "15-05-2018", "nav": "22.91490"}, {"date": "15-03-2018", "nav": "22.46870"}, {"date": "15-02-2018", "nav": "22.71940"}, {"date": "15-01-2018", "nav": "23.40710"}, {"date": "15-12-2017", "nav": "22.77200"}, {"date": "15-11-2017", "nav": "22.25210"}, {"date": "15-09-2017", "nav": "22.48840"}, {"date": "15-06-2017", "nav": "21.16360"}, {"date": "15-05-2017", "nav": "20.94610"}, {"date": "15-03-2017", "nav": "19.84660"}, {"date": "15-02-2017", "nav": "19.35590"}, {"date": "15-12-2016", "nav": "18.18270"}, {"date": "15-11-2016", "nav": "18.21510"}, {"date": "15-09-2016", "nav": "19.06400"}, {"date": "15-07-2016", "nav": "18.19980"}, {"date": "15-06-2016", "nav": "17.56490"}, {"date": "15-03-2016", "nav": "16.12570"}, {"date": "15-02-2016", "nav": "15.71800"}, {"date": "15-01-2016", "nav": "16.16710"}, {"date": "15-12-2015", "nav": "16.45590"}, {"date": "15-10-2015", "nav": "16.89330"}, {"date": "15-09-2015", "nav": "16.41930"}, {"date": "15-07-2015", "nav": "17.00190"}, {"date": "15-06-2015", "nav": "16.14240"}, {"date": "15-05-2015", "nav": "16.41270"}, {"date": "15-04-2015", "nav": "17.00180"}, {"date": "15-01-2015", "nav": "16.29330"}, {"date": "15-12-2014", "nav": "15.71800"}]